biomaj_download/__init__.py
biomaj_download/biomaj_download_web.py
biomaj_download/downloadclient.py
biomaj_download/downloadservice.py
biomaj_download/wsgi.py
biomaj_download/download/__init__.py
biomaj_download/download/curl.py
biomaj_download/download/direct.py
biomaj_download/download/downloadthreads.py
biomaj_download/download/interface.py
biomaj_download/download/localcopy.py
biomaj_download/download/protocolirods.py
biomaj_download/download/rsync.py
biomaj_download/message/__init__.py
biomaj_download/message/downmessage_pb2.py
biomaj_download-3.2.12.data/scripts/biomaj_download_consumer.py
biomaj_download-3.2.12.dist-info/LICENSE
biomaj_download-3.2.12.dist-info/METADATA
biomaj_download-3.2.12.dist-info/WHEEL
biomaj_download-3.2.12.dist-info/top_level.txt
biomaj_download-3.2.12.dist-info/RECORD
