Metadata-Version: 2.1
Name: biomaj_download
Version: 3.2.12
Summary: BioMAJ download service
Home-page: https://biomaj.genouest.org
Download-URL: https://biomaj.genouest.org
Author: GenOuest platform
Author-email: support@genouest.org
Classifier: Development Status :: 5 - Production/Stable
Classifier: Environment :: Console
Classifier: Natural Language :: English
Classifier: Operating System :: POSIX :: Linux
Classifier: Intended Audience :: Science/Research
Classifier: Topic :: Scientific/Engineering :: Bio-Informatics
Classifier: License :: OSI Approved :: GNU Affero General Public License v3 or later (AGPLv3+)
Classifier: Programming Language :: Python :: 3 :: Only
Classifier: Programming Language :: Python :: 3.6
Requires-Python: >=3.6, <4
License-File: LICENSE
Requires-Dist: pycurl
Requires-Dist: py-bcrypt
Requires-Dist: pika ==0.13.0
Requires-Dist: redis
Requires-Dist: PyYAML
Requires-Dist: protobuf ==3.20.3
Requires-Dist: flask
Requires-Dist: python-consul
Requires-Dist: prometheus-client >=0.0.18
Requires-Dist: requests
Requires-Dist: biomaj-core >=3.0.19
Requires-Dist: biomaj-zipkin
Requires-Dist: humanfriendly
Requires-Dist: python-irodsclient
Requires-Dist: simpleeval
Requires-Dist: tenacity
Requires-Dist: ftputil
